richfile/__init__.py
richfile/demo.py
richfile/functions.py
richfile/util.py
richfile-0.5.2.dist-info/METADATA
richfile-0.5.2.dist-info/WHEEL
richfile-0.5.2.dist-info/top_level.txt
richfile-0.5.2.dist-info/RECORD
