Metadata-Version: 2.4
Name: richfile
Version: 0.5.2
Summary: A library for reading and writing hierarchical data files
Home-page: https://github.com/RichieHakim/richfile
Author: Richard Hakim
License: LICENSE
Keywords: data analysis,machine learning,neuroscience
Requires-Dist: filelock>3.15
Requires-Dist: hypothesis
Dynamic: author
Dynamic: description
Dynamic: description-content-type
Dynamic: home-page
Dynamic: keywords
Dynamic: license
Dynamic: requires-dist
Dynamic: summary
